starbug2/__init__.py
starbug2/artificialstars.py
starbug2/mask.py
starbug2/matching.py
starbug2/misc.py
starbug2/param.py
starbug2/routines.py
starbug2/starbug.py
starbug2/utils.py
starbug2/bin/__init__.py
starbug2/bin/ast.py
starbug2/bin/main.py
starbug2/bin/match.py
starbug2/extras/.default.param
starbug2/extras/starbug2-ast.completion
starbug2/extras/starbug2-match.completion
starbug2/extras/starbug2.completion
starbug2-0.7.7.dist-info/LICENSE.txt
starbug2-0.7.7.dist-info/METADATA
starbug2-0.7.7.dist-info/WHEEL
starbug2-0.7.7.dist-info/entry_points.txt
starbug2-0.7.7.dist-info/top_level.txt
starbug2-0.7.7.dist-info/RECORD
