Metadata-Version: 2.1
Name: starbug2
Version: 0.7.7
Summary: JWST PSF photometry in complex crowded fields.
Author-email: Conor Nally <conor.nally@ed.ac.uk>
License: GNU GENERAL PUBLIC LICENSE
Project-URL: Documentation, https://starbug2.readthedocs.io/en/latest/
Project-URL: Repository, https://github.com/conornally/starbug2.git
Requires-Python: >=3.10
License-File: LICENSE.txt
Requires-Dist: numpy >=1.25
Requires-Dist: photutils ==1.13.0
Requires-Dist: astropy
Requires-Dist: parse
Requires-Dist: scipy
Requires-Dist: webbpsf
Requires-Dist: scikit-image
Requires-Dist: matplotlib
